<?xml version='1.0' encoding='utf-8'?>
<CalendarEvents><Event><Summary>Tamil Thai Pongal Day</Summary><Catagories>Public,Bank,Mercantile</Catagories><Start>2021-01-14</Start><End>2021-01-15</End></Event><Event><Summary>Duruthu Full Moon Poya Day</Summary><Catagories>Public,Bank</Catagories><Start>2021-01-28</Start><End>2021-01-29</End></Event><Event><Summary>Independence Day</Summary><Catagories>Public,Bank,Mercantile</Catagories><Start>2021-02-04</Start><End>2021-02-05</End></Event><Event><Summary>Nawam Full Moon Poya Day</Summary><Catagories>Public,Bank</Catagories><Start>2021-02-26</Start><End>2021-02-27</End></Event><Event><Summary>Maha sivarathri Day</Summary><Catagories>Public,Bank</Catagories><Start>2021-03-11</Start><End>2021-03-12</End></Event><Event><Summary>Madin Full Moon Poya Day</Summary><Catagories>Public,Bank</Catagories><Start>2021-03-28</Start><End>2021-03-29</End></Event><Event><Summary>Good Friday</Summary><Catagories>Public,Bank</Catagories><Start>2021-04-02</Start><End>2021-04-03</End></Event><Event><Summary>Day prior to Sinhala &amp; Tamil New Year Day</Summary><Catagories>Public,Bank,Mercantile</Catagories><Start>2021-04-13</Start><End>2021-04-14</End></Event><Event><Summary>Sinhala &amp; Tamil New Year Day</Summary><Catagories>Public,Bank,Mercantile</Catagories><Start>2021-04-14</Start><End>2021-04-15</End></Event><Event><Summary>Bak Full Moon Poya Day</Summary><Catagories>Public,Bank</Catagories><Start>2021-04-26</Start><End>2021-04-27</End></Event><Event><Summary>May Day</Summary><Catagories>Public,Bank,Mercantile</Catagories><Start>2021-05-01</Start><End>2021-05-02</End></Event><Event><Summary>Id-Ul-Fitr (Ramazan Festival Day)</Summary><Catagories>Public,Bank</Catagories><Start>2021-05-14</Start><End>2021-05-15</End></Event><Event><Summary>Vesak Full Moon Poya Day</Summary><Catagories>Public,Bank</Catagories><Start>2021-05-26</Start><End>2021-05-27</End></Event><Event><Summary>Day following Vesak Full Moon Poya Day</Summary><Catagories>Public,Bank,Mercantile</Catagories><Start>2021-05-27</Start><End>2021-05-28</End></Event><Event><Summary>Poson Full Moon Poya Day</Summary><Catagories>Public,Bank</Catagories><Start>2021-06-24</Start><End>2021-06-25</End></Event><Event><Summary>Id-Ul-Alha (Hadji Festival Day)</Summary><Catagories>Public,Bank</Catagories><Start>2021-07-21</Start><End>2021-07-22</End></Event><Event><Summary>Esala Full Moon Poya Day</Summary><Catagories>Public,Bank</Catagories><Start>2021-07-23</Start><End>2021-07-24</End></Event><Event><Summary>Nikini Full Moon Poya Day</Summary><Catagories>Public,Bank</Catagories><Start>2021-08-22</Start><End>2021-08-23</End></Event><Event><Summary>Binara Full Moon Poya Day</Summary><Catagories>Public,Bank</Catagories><Start>2021-09-20</Start><End>2021-09-21</End></Event><Event><Summary>Milad-Un-Nabi (Holy Prophet’s Birthday)</Summary><Catagories>Public,Bank,Mercantile</Catagories><Start>2021-10-19</Start><End>2021-10-20</End></Event><Event><Summary>Vap Full Moon Poya Day</Summary><Catagories>Public,Bank</Catagories><Start>2021-10-20</Start><End>2021-10-21</End></Event><Event><Summary>Deepavali Festival Day</Summary><Catagories>Public,Bank</Catagories><Start>2021-11-04</Start><End>2021-11-05</End></Event><Event><Summary>Il Full Moon Poya Day</Summary><Catagories>Public,Bank</Catagories><Start>2021-11-18</Start><End>2021-11-19</End></Event><Event><Summary>Unduvap Full Moon Poya Day</Summary><Catagories>Public,Bank</Catagories><Start>2021-12-18</Start><End>2021-12-19</End></Event><Event><Summary>Christmas Day</Summary><Catagories>Public,Bank,Mercantile</Catagories><Start>2021-12-25</Start><End>2021-12-26</End></Event><Event><Summary>Test Event 2</Summary><Catagories>Public,Bank,Mercantile</Catagories><Start>2021-12-25</Start><End>2021-12-26</End></Event></CalendarEvents>